ostk/__init__.py
ostk/cli.py
ostk/rebuild.py
ostk/agent/__init__.py
ostk/agent/agent.py
ostk/agent/providers/__init__.py
ostk/agent/providers/base.py
ostk/agent/providers/factory.py
ostk/agent/providers/groq_provider.py
ostk/agent/providers/ollama_provider.py
ostk/agent/providers/openai_provider.py
ostk-0.1.0.dist-info/METADATA
ostk-0.1.0.dist-info/WHEEL
ostk-0.1.0.dist-info/entry_points.txt
ostk-0.1.0.dist-info/top_level.txt
ostk-0.1.0.dist-info/RECORD
