Metadata-Version: 2.4
Name: ostk
Version: 0.1.0
Summary: OSTK (OpenSky ToolKit) - Nifty tools for opensky with good vibes
Requires-Python: >=3.12
Requires-Dist: appdirs>=1.4.4
Requires-Dist: click>=8.1.0
Requires-Dist: prompt_toolkit>=3.0.43
Requires-Dist: numpy>=2.3.4
Requires-Dist: pymodes>=2.21.1
Requires-Dist: pyopensky>=2.15
Requires-Dist: ollama>=0.1.0
Requires-Dist: openai>=1.0.0
Requires-Dist: rich>=13.0.0
